MANIFEST.in
README.rst
setup.py
collective/__init__.py
collective.regexredirector.egg-info/PKG-INFO
collective.regexredirector.egg-info/SOURCES.txt
collective.regexredirector.egg-info/dependency_links.txt
collective.regexredirector.egg-info/entry_points.txt
collective.regexredirector.egg-info/namespace_packages.txt
collective.regexredirector.egg-info/not-zip-safe
collective.regexredirector.egg-info/requires.txt
collective.regexredirector.egg-info/top_level.txt
collective/regexredirector/__init__.py
collective/regexredirector/configure.zcml
collective/regexredirector/interfaces.py
collective/regexredirector/rebuild_i18n.sh
collective/regexredirector/regexstorage.py
collective/regexredirector/testing.py
collective/regexredirector/browser/__init__.py
collective/regexredirector/browser/browser.py
collective/regexredirector/browser/configure.zcml
collective/regexredirector/browser/controlpanel.py
collective/regexredirector/browser/interfaces.py
collective/regexredirector/locales/collective.regexredirector.pot
collective/regexredirector/locales/en/LC_MESSAGES/collective.regexredirector.po
collective/regexredirector/locales/fr/LC_MESSAGES/collective.regexredirector.po
collective/regexredirector/profiles/default/browserlayer.xml
collective/regexredirector/profiles/default/componentregistry.xml
collective/regexredirector/profiles/default/controlpanel.xml
collective/regexredirector/profiles/default/metadata.xml
collective/regexredirector/profiles/default/registry.xml
collective/regexredirector/tests/__init__.py
collective/regexredirector/tests/base.py
collective/regexredirector/tests/browser.txt
collective/regexredirector/tests/layer.py
collective/regexredirector/tests/test_doctest.py
collective/regexredirector/tests/test_regexredirectors.py
collective/regexredirector/tests/test_setup.py
collective/regexredirector/upgrades/__init__.py
collective/regexredirector/upgrades/configure.zcml
collective/regexredirector/upgrades/v1x.py
docs/HISTORY.txt