Metadata-Version: 1.1
Name: collective.regexredirector
Version: 0.2.1
Summary: Addon for plone.app.redirector concerning regex redirector
Home-page: https://github.com/collective/collective.regexredirector
Author: Julien Marinescu aka davisp1
Author-email: davisp%40xenbox.fr
License: GPL
Keywords: plone
Platform: UNKNOWN
Classifier: Environment :: Web Environment
Classifier: License :: OSI Approved :: GNU General Public License (GPL)
Classifier: Operating System :: OS Independent
Classifier: Framework :: Zope2
Classifier: Framework :: Plone
Classifier: Framework :: Plone :: 4.0
Classifier: Framework :: Plone :: 4.1
Classifier: Framework :: Plone :: 4.2
Classifier: Framework :: Plone :: 4.3
Classifier: Programming Language :: Python
Classifier: Programming Language :: Python :: 2.6
Classifier: Programming Language :: Python :: 2.7
